Euclid/__init__.py
Euclid/euclid.py
Euclid_FasterCoding-0.1.0.dist-info/METADATA
Euclid_FasterCoding-0.1.0.dist-info/WHEEL
Euclid_FasterCoding-0.1.0.dist-info/top_level.txt
Euclid_FasterCoding-0.1.0.dist-info/RECORD
