Metadata-Version: 2.1
Name: Euclid-FasterCoding
Version: 0.1.0
Summary: Example for the euclidean gcd and extgcd algorithm
Home-page: https://github.com/FasterCoding/Greatest-Common-Divisor
Author: FasterCoding
Author-email: fastercodingtutorial@gmail.com
License: UNKNOWN
Platform: UNKNOWN
Classifier: Programming Language :: Python :: 3
Classifier: License :: OSI Approved :: MIT License
Classifier: Operating System :: OS Independent
